a_pandas_ex_console_plot/LICENSE
a_pandas_ex_console_plot/README.MD
a_pandas_ex_console_plot/__init__.py
a_pandas_ex_console_plot/requirements.txt
a_pandas_ex_console_plot/thirdparty.json
a_pandas_ex_console_plot-0.10.dist-info/LICENSE.rst
a_pandas_ex_console_plot-0.10.dist-info/METADATA
a_pandas_ex_console_plot-0.10.dist-info/WHEEL
a_pandas_ex_console_plot-0.10.dist-info/top_level.txt
a_pandas_ex_console_plot-0.10.dist-info/RECORD
